[
  {
    "id_number": "594673747963",
    "full_name": "VŨ THANH TÙNG",
    "date_of_birth": "29/09/1972",
    "gender": "Nam",
    "nationality": "Việt Nam",
    "place_of_origin": "Đồng Nai",
    "place_of_residence": "362/96/26 Điện Biên Phủ, KP3, Phường Cao Thắng, Đà Nẵng",
    "date_of_expiry": "13/11/2031"
  },
  {
    "id_number": "185529065328",
    "full_name": "PHAN ĐỨC THẮNG",
    "date_of_birth": "27/10/1981",
    "gender": "Nữ",
    "nationality": "Việt Nam",
    "place_of_origin": "Nghệ An",
    "place_of_residence": "Số 12 Nam Kỳ Khởi Nghĩa, Phường Tân Phú, Quận 3, Hà Nội",
    "date_of_expiry": "10/11/2031"
  },
  {
    "id_number": "585931742457",
    "full_name": "HỒ THỊ HOA",
    "date_of_birth": "07/07/1986",
    "gender": "Nữ",
    "nationality": "Việt Nam",
    "place_of_origin": "Huế",
    "place_of_residence": "Thôn An, Xã Tân Hà, Quận Bình Thạnh, Bắc Giang",
    "date_of_expiry": "09/06/2032"
  },
  {
    "id_number": "292885090081",
    "full_name": "ĐẶNG NGỌC HÀ",
    "date_of_birth": "29/06/1960",
    "gender": "Nữ",
    "nationality": "Việt Nam",
    "place_of_origin": "Hải Phòng",
    "place_of_residence": "47/4/1 Cách Mạng Tháng 8, KP1, Phường 3, Cần Thơ",
    "date_of_expiry": "16/02/2030"
  },
  {
    "id_number": "486545450890",
    "full_name": "ĐỖ THỊ BÍCH",
    "date_of_birth": "04/01/1962",
    "gender": "Nam",
    "nationality": "Việt Nam",
    "place_of_origin": "Bình Dương",
    "place_of_residence": "620/8/8 Trần Hưng Đạo, KP1, Xã Lộc Tân, An Giang",
    "date_of_expiry": "14/07/2031"
  },
  {
    "id_number": "903173908403",
    "full_name": "NGUYỄN ĐỨC THẮNG",
    "date_of_birth": "18/10/1974",
    "gender": "Nam",
    "nationality": "Việt Nam",
    "place_of_origin": "Huế",
    "place_of_residence": "Phường Tân Phú, Quận Hải Châu, Gia Lai",
    "date_of_expiry": "26/01/2032"
  },
  {
    "id_number": "937858310051",
    "full_name": "HỒ NGỌC HÀ",
    "date_of_birth": "02/05/1984",
    "gender": "Nam",
    "nationality": "Việt Nam",
    "place_of_origin": "Đà Nẵng",
    "place_of_residence": "Số 35 Nguyễn Huệ, Thôn Phủ Mỹ, Quận Bình Thạnh, Huế",
    "date_of_expiry": "14/04/2031"
  },
  {
    "id_number": "802158938432",
    "full_name": "NGÔ VĂN AN",
    "date_of_birth": "02/07/1972",
    "gender": "Nữ",
    "nationality": "Việt Nam",
    "place_of_origin": "Lâm Đồng",
    "place_of_residence": "271/91/16 Nam Kỳ Khởi Nghĩa, KP4, Xã Quế Xuân 2, Quảng Ninh",
    "date_of_expiry": "15/08/2032"
  },
  {
    "id_number": "699698632255",
    "full_name": "NGUYỄN VĂN NAM",
    "date_of_birth": "13/09/1984",
    "gender": "Nữ",
    "nationality": "Việt Nam",
    "place_of_origin": "Hồ Chí Minh",
    "place_of_residence": "Số 242 Điện Biên Phủ, Phường Lộc Sơn, Quận 5, Đắk Lắk",
    "date_of_expiry": "16/07/2032"
  },
  {
    "id_number": "376647061137",
    "full_name": "ĐẶNG THỊ LAN",
    "date_of_birth": "30/03/1967",
    "gender": "Nam",
    "nationality": "Việt Nam",
    "place_of_origin": "Đà Nẵng",
    "place_of_residence": "Số 54 Phan Chu Trinh, Phường 3, Quận 7, Quảng Ninh",
    "date_of_expiry": "03/03/2030"
  },
  {
    "id_number": "176059850296",
    "full_name": "TRẦN THỊ MAI",
    "date_of_birth": "20/11/1993",
    "gender": "Nữ",
    "nationality": "Việt Nam",
    "place_of_origin": "Hải Phòng",
    "place_of_residence": "Phường Cao Thắng, Huyện Gia Lâm, Hải Phòng",
    "date_of_expiry": "18/08/2032"
  },
  {
    "id_number": "966664912169",
    "full_name": "LÊ XUÂN TRƯỜNG",
    "date_of_birth": "07/06/1994",
    "gender": "Nam",
    "nationality": "Việt Nam",
    "place_of_origin": "Thái Nguyên",
    "place_of_residence": "Số 118 Phan Chu Trinh, Phường Tân Phú, Thành phố Hạ Long, Đồng Nai",
    "date_of_expiry": "29/07/2028"
  },
  {
    "id_number": "936362754662",
    "full_name": "LÝ THỊ THU",
    "date_of_birth": "19/08/1984",
    "gender": "Nam",
    "nationality": "Việt Nam",
    "place_of_origin": "Hồ Chí Minh",
    "place_of_residence": "Xã Quế Xuân 2, Quận 5, Nghệ An",
    "date_of_expiry": "25/01/2028"
  },
  {
    "id_number": "367106821072",
    "full_name": "NGÔ BẢO CHÂU",
    "date_of_birth": "21/03/1990",
    "gender": "Nữ",
    "nationality": "Việt Nam",
    "place_of_origin": "Khánh Hòa",
    "place_of_residence": "121/52/28 Hai Bà Trưng, KP3, Phường 3, Bình Dương",
    "date_of_expiry": "17/05/2033"
  },
  {
    "id_number": "297646477816",
    "full_name": "DƯƠNG VĂN NAM",
    "date_of_birth": "24/12/1962",
    "gender": "Nam",
    "nationality": "Việt Nam",
    "place_of_origin": "Hà Nội",
    "place_of_residence": "Thôn Phủ Mỹ, Thôn Phủ Mỹ, Huyện Đức Trọng, Gia Lai",
    "date_of_expiry": "17/12/2026"
  },
  {
    "id_number": "309367200359",
    "full_name": "VŨ VĂN AN",
    "date_of_birth": "27/09/1990",
    "gender": "Nam",
    "nationality": "Việt Nam",
    "place_of_origin": "Đắk Lắk",
    "place_of_residence": "195/43/2 Phan Chu Trinh, KP4, Phường 3, Đắk Lắk",
    "date_of_expiry": "07/03/2029"
  },
  {
    "id_number": "939516310592",
    "full_name": "HỒ VĂN CƯỜNG",
    "date_of_birth": "15/12/1992",
    "gender": "Nam",
    "nationality": "Việt Nam",
    "place_of_origin": "Thanh Hóa",
    "place_of_residence": "Thôn An, Xã Lộc Tân, Quận Hoàn Kiếm, Đà Nẵng",
    "date_of_expiry": "20/02/2029"
  },
  {
    "id_number": "752767977585",
    "full_name": "HỒ THỊ HÀ",
    "date_of_birth": "22/08/2001",
    "gender": "Nam",
    "nationality": "Việt Nam",
    "place_of_origin": "Hồ Chí Minh",
    "place_of_residence": "Thôn Tân, Xã Lộc Tân, Quận 3, Hải Phòng",
    "date_of_expiry": "02/03/2034"
  },
  {
    "id_number": "815596454238",
    "full_name": "LÝ QUỐC HUY",
    "date_of_birth": "21/11/1997",
    "gender": "Nữ",
    "nationality": "Việt Nam",
    "place_of_origin": "Hà Nội",
    "place_of_residence": "Phường 3, Thành phố Hạ Long, Bắc Giang",
    "date_of_expiry": "29/05/2031"
  },
  {
    "id_number": "170408758827",
    "full_name": "ĐẶNG THỊ HOA",
    "date_of_birth": "14/10/1986",
    "gender": "Nữ",
    "nationality": "Việt Nam",
    "place_of_origin": "Nghệ An",
    "place_of_residence": "Số 97 H. Tấn Phát, Phường Tân Phú, Quận Ngũ Hành Sơn, Hải Phòng",
    "date_of_expiry": "09/04/2033"
  }
]